<?xml version="1.0"?>

<PropertyList>
  <path>Aircraft/f16/Models/Armament/External-stores/370G.ac</path>
  <effect>
      <inherits-from>Aircraft/f16/Models/Effects/fuselage/model-combined-fuselage</inherits-from>
      <parameters>
          <metallic type="float">0.80</metallic>
          <ambient-factor type="float">0.35</ambient-factor>
          <rain-enabled type="int">0</rain-enabled>
          <ambient-correction type="float">0.00</ambient-correction>
          <reflection-enabled type="int">0</reflection-enabled>
      </parameters>
      <object-name>fuel_tank370</object-name>
  </effect>

 </PropertyList>